operacoes_matematicas/__init__.py
operacoes_matematicas/multiplicacao_e_divisao.py
operacoes_matematicas/soma_e_subtrai.py
operacoes_matematicas_teste-0.0.3.dist-info/METADATA
operacoes_matematicas_teste-0.0.3.dist-info/WHEEL
operacoes_matematicas_teste-0.0.3.dist-info/top_level.txt
operacoes_matematicas_teste-0.0.3.dist-info/RECORD
