Metadata-Version: 2.1
Name: operacoes-matematicas-teste
Version: 0.0.3
Summary: Pacote python que faz operações matemáticas simples
Home-page: https://github.com/rykardoassets/operacoes_matematicas
Author: Ricardo Duarte
Author-email: rykardo.contato@gmail.com
License: UNKNOWN
Platform: UNKNOWN
Requires-Python: >=3.8
